<!DOCTYPE frameset SYSTEM "frameset.dtd">


<frameset>
<predicate lemma="denominate">
<note>
  Frames file for 'denominate' based on survey of sentences in the WSJ
  corpus. 
</note>

<roleset id="denominate.01" name=", give a name, assign a designation to" vncls="-">
<roles>
  <role n="0"  descr="agent"/>
  <role n="1"  descr="entity named"/>
  <role n="2"  descr="attribute"/>
</roles>


<example name="passive">
<inflection person="ns" tense="present" aspect="ns" voice="passive" form="participle"/>
<text>
 Because the funds ' investments are denominated [*-1] in foreign currencies , their value expressed [*] in dollars goes up when those currencies rise against the dollar [*T*-2] .
</text>
	<rel>denominated</rel>
	<arg n="1">[*-1] ->  the funds ' investments</arg>
	<arg n="2" f="in">foreign currencies</arg>
</example>


</roleset>
</predicate>

<note>
  frames created by Olga
</note>

</frameset>
