<!DOCTYPE frameset SYSTEM "frameset.dtd">


<frameset>
<predicate lemma="holler">
<note>
  Frames file for 'holler' based on survey of sentences in the WSJ
  corpus. 
</note>

<roleset id="holler.01" name="to shout, yell"
vncls="37.3">
<roles>
  <role n="0"  descr="agent"/>
  <role n="1"  descr="utterance, holler about"/>
</roles>

<example name="intransitive">
<inflection person="ns" tense="present" aspect="ns" voice="active" form="full"/>
<text>
 When it was n't my turn in the balloon [*T*-2] I followed its progress from the `` chase car , '' [*-1] listening to the driver holler into a walkie-talkie .
</text>
	<arg n="0">the driver</arg>
	<rel>holler</rel>
	<arg n="M" f="DIR">into a walkie-talkie</arg>
</example>


</roleset>
</predicate>

<note>
  frames created by Olga
</note>

</frameset>

